lab1_imul/logs/annotated/trace.v
//      // verilator_coverage annotation
        //========================================================================
        // Line Tracing
        //========================================================================
        
        `ifndef VC_TRACE_V
        `define VC_TRACE_V
        import "DPI-C" function void pass() ;
        import "DPI-C" function void fail() ;
        
        // NOTE: This macro is declared outside of the module to allow some vc
        // modules to see it and use it in their own params. Verilog does not
        // allow other modules to hierarchically reference the nbits localparam
        // inside this module in constant expressions (e.g., localparams).
        
        `define VC_TRACE_NCHARS 512
        `define VC_TRACE_NBITS  512*8
        
        module vc_Trace
        (
 001617   input logic clk,
 000001   input logic reset
        );
        
          integer len0;
          integer len1;
          integer idx0;
          integer idx1;
        
          // NOTE: If you change these, then you also need to change the
          // hard-coded constant in the declaration of the trace function at the
          // bottom of this file.
          // NOTE: You would also need to change the VC_TRACE_NBITS and
          // VC_TRACE_NCHARS macro at the top of this file.
        
          localparam nchars = 512;
          localparam nbits  = 512*8;
        
          // This is the actual trace storage used when displaying a trace
        
          logic [nbits-1:0] storage;
        
          // Meant to be accesible from outside module
        
%000000   integer cycles_next = 0;
%000000   integer cycles      = 0;
        
          // Get trace level from command line
        
%000000   logic [3:0] level;
        
        `ifndef VERILATOR
          initial begin
            storage = '0;
            storage[31:0] = 511; 
            $display("Strating Trace");
            if ( !$value$plusargs( "trace=%d", level ) ) begin
              level = 0;
        
            end
          end
        `else
%000000   initial begin
%000000       storage = '0;
%000000       storage[31:0] = 511; 
%000000     level = 1;
          end
        `endif // !`ifndef VERILATOR
        
          // Track cycle count
        
 000808   always_ff @( posedge clk ) begin
 000808     cycles <= ( reset ) ? 0 : cycles_next;
          end
        
          //----------------------------------------------------------------------
          // append_str
          //----------------------------------------------------------------------
          // Appends a string to the trace.
        
 004252   task append_str
          (
            inout logic [nbits-1:0] trace,
            input logic [nbits-1:0] str
          );
 004252   begin
 004252     trace=trace;
        
 004252     len0 = 1;
 025472     while ( str[len0*8+:8] != 0 ) begin
 025472       len0 = len0 + 1;
            end
        
 004252     idx0 = trace[31:0];
        
 004252     for ( idx1 = len0-1; idx1 >= 0; idx1 = idx1 - 1 )
 029724     begin
 029724       trace[ idx0*8 +: 8 ] = str[ idx1*8 +: 8 ];
              //$display("Storing %d at %d",str[ idx1*8 +: 8 ],idx0);
 029724       $write("%c",str[ idx1*8 +: 8 ]);
 029724       idx0 = idx0 - 1;
            end
        
 004252     trace[31:0] = idx0;
        
          end
          endtask
        
          //----------------------------------------------------------------------
          // append_str_ljust
          //----------------------------------------------------------------------
          // Appends a left-justified string to the trace.
        
%000000   task append_str_ljust
          (
            inout logic [nbits-1:0] trace,
            input logic [nbits-1:0] str
          );
%000000   begin
        
%000000     idx0 = trace[31:0];
%000000     idx1 = nchars;
        
%000000     while ( str[ idx1*8-1 -: 8 ] != 0 ) begin
%000000       trace[ idx0*8 +: 8 ] = str[ idx1*8-1 -: 8 ];
%000000       idx0 = idx0 - 1;
%000000       idx1 = idx1 - 1;
            end
        
%000000     trace[31:0] = idx0;
        
          end
          endtask
        
          //----------------------------------------------------------------------
          // append_chars
          //----------------------------------------------------------------------
          // Appends the given number of characters to the trace.
        
 001504   task append_chars
          (
            inout logic   [nbits-1:0] trace,
            input logic         [7:0] char,
            input integer             num
          );
 001504   begin
 001504     trace=trace;
 001504     idx0 = trace[31:0];
        
 001504     for ( idx1 = 0;
 020588           idx1 < num;
 020588           idx1 = idx1 + 1 )
 020588     begin
 020588       trace[idx0*8+:8] = char;
              //$display("Storing %d at %d",char,idx0);
 020588       $write("%c",char);
 020588       idx0 = idx0 - 1;
            end
        
 001504     trace[31:0] = idx0;
        
          end
          endtask
        
          //----------------------------------------------------------------------
          // append_val_str
          //----------------------------------------------------------------------
          // Append a string modified by val signal.
        
%000000   task append_val_str
          (
            inout logic [nbits-1:0] trace,
            input logic             val,
            input logic [nbits-1:0] str
          );
%000000   begin
        
%000000     len1 = 0;
%000000     while ( str[len1*8+:8] != 0 ) begin
%000000       len1 = len1 + 1;
            end
        
%000000     if ( val )
%000000       append_str( trace, str );
%000000     else if ( !val )
%000000       append_chars( trace, " ", len1 );
%000000     else begin
%000000       append_str( trace, "x" );
%000000       append_chars( trace, " ", len1-1 );
            end
        
          end
          endtask
        
          //----------------------------------------------------------------------
          // val_rdy_str
          //----------------------------------------------------------------------
          // Append a string modified by val/rdy signals.
        
 001616   task append_val_rdy_str
          (
            inout logic [nbits-1:0] trace,
            input logic             val,
            input logic             rdy,
            input logic [nbits-1:0] str
          );
 001616   begin
        
 001616     len1 = 0;
 022796     while ( str[len1*8+:8] != 0 ) begin
 022796       len1 = len1 + 1;
            end
        
 000112     if ( rdy && val ) begin
 000112       append_str( trace, str );
            end
 000752     else if ( rdy && !val ) begin
 000752       append_chars( trace, " ", len1 );
            end
 000672     else if ( !rdy && val ) begin
 000672       append_str( trace, "#" );
 000672       append_chars( trace, " ", len1-1 );
            end
%000000     else if ( !rdy && !val ) begin
 000080       append_str( trace, "." );
 000080       append_chars( trace, " ", len1-1 );
            end
%000000     else begin
%000000       append_str( trace, "x" );
%000000       append_chars( trace, " ", len1-1 );
            end
        
          end
          endtask
        
        endmodule
        
        //------------------------------------------------------------------------
        // VC_TRACE_NBITS_TO_NCHARS
        //------------------------------------------------------------------------
        // Macro to determine number of characters for a net
        
        `define VC_TRACE_NBITS_TO_NCHARS( nbits_ ) ((nbits_+3)/4)
        
        //------------------------------------------------------------------------
        // VC_TRACE_BEGIN
        //------------------------------------------------------------------------
        
        //`define VC_TRACE_BEGIN                                                  \
        //  export "DPI-C" task line_trace;                                       \
        //  vc_Trace vc_trace(clk,reset);                                         \
        //  task line_trace( inout bit [(512*8)-1:0] trace_str );
        
        `ifdef VERILATOR
        `define VC_TRACE_BEGIN                                        \
          /*verilator coverage_off*/          \
          integer idx1;                                                \
          integer idx0;                                                \
          vc_Trace vc_trace(clk,reset);                                         \
                                                                                \
          task display_trace;                                                   \
          begin                                                                 \
            /*vc_trace.storage = '0;*/                                                                    \
            vc_trace.storage[31:0] = 511;                                                                    \
                                                                                \
            if ( vc_trace.level > 0 ) begin                                     \
              \
               /*$display("getting trace");  */                                                               \
              $write( "%4d: ", vc_trace.cycles );                               \
              line_trace( vc_trace.storage );                                   \
                                                                                \
                                                                                \
              vc_trace.idx0 = vc_trace.storage[31:0];                           \
               idx0=vc_trace.idx0 ;                                      \
              \
              /*$display ("Output Trace %d to %d", idx0,vc_trace.nchars-1);    */                               \
              for ( idx1 = vc_trace.nchars-1;                          \
                    idx1 > idx0;                              \
                    idx1 = idx1- 1 )                         \
              begin                                                             \
                /*$write( "%d,%d",idx1, vc_trace.storage[vc_trace.idx1*8+:8] );           \
                $display("Retriving %d at %d",vc_trace.storage[vc_trace.idx1*8+:8] ,idx1); */                  \
              end                                                               \
              $write("\n");                                                     \
                                                                                \
            end                                                                 \
            vc_trace.cycles_next = vc_trace.cycles + 1;                         \
                                                                                \
          end                                                                   \
          endtask                                                               \
                                                                                \
          task line_trace( inout bit [(512*8)-1:0] trace_str );
        `else
        `define VC_TRACE_BEGIN                                                  \
          export "DPI-C" task line_trace;                                       \
          vc_Trace vc_trace(clk,reset);                                         \
          task line_trace( inout bit [(512*8)-1:0] trace_str );
        `endif
        
        //------------------------------------------------------------------------
        // VC_TRACE_END
        //------------------------------------------------------------------------
        
        `define VC_TRACE_END \
          /*verilator coverage_on*/ \
          endtask
        
        `endif /* VC_TRACE_V */

lab2_proc/ProcDpathImmGen.v
//========================================================================
// Proc Datapath Immediate Generation
//========================================================================
// Generate intermediate (imm) based on type

`ifndef LAB2_PROC_PROC_DPATH_IMM_GEN_V
`define LAB2_PROC_PROC_DPATH_IMM_GEN_V

module lab2_proc_ProcDpathImmGen
(
  input  logic [ 2:0] imm_type,
  input  logic [31:0] inst,
  output logic [31:0] imm
);

  always_comb begin
    case ( imm_type )
      3'd0: // I-type
        imm = { {21{inst[31]}}, inst[30:25], inst[24:21], inst[20] };

      3'd2: // B-type
        imm = { {20{inst[31]}}, inst[7], inst[30:25], inst[11:8], 1'b0 };

      3'd3: // U-type
        imm = { inst[31:12], 12'b0 };

      3'd4: // J-type
        imm = { {12{inst[31]}}, inst[19:12], inst[20], inst[30:25], inst[24:21], 1'b0 };
      default:
        imm = 32'bx;

    endcase
  end

endmodule

`endif /* LAB2_PROC_DPATH_IMM_GEN_V */

lab2_proc/utb_ProcDpathImmGen.v
//========================================================================
// utb_ProcDpathImmGen
//========================================================================
// A basic Verilog unit test bench for the Processor ImmGen module

`default_nettype none
`timescale 1ps/1ps

`include "ProcDpathImmGen.v"
`include "vc/trace.v"

//------------------------------------------------------------------------
// Top-level module
//------------------------------------------------------------------------

module top(   input logic clk ,  input logic linetrace  );

  logic [ 2:0] imm_type;
  logic [31:0] inst;

  logic [31:0] imm;

  // Instantiate the processor ALU
  lab2_proc_ProcDpathImmGen
  DUT
  ( .*
  ); 

  //----------------------------------------------------------------------
  // Run the Test Bench
  //----------------------------------------------------------------------

  initial begin
    @(negedge clk);
    
    //======================================
    // Test I-type
    //======================================

    // 1. ADDI 
    // Set inputs
    imm_type = 0;
    inst     = 'b100101010101_01010_000_10101_0010011;

    #1

    // Check the result
    check_result('b11111111111111111111_100101010101, "I-type");

    // 2. ANDI
    imm_type = 0;
    inst     = 'b000101010101_01010_111_10101_0010011;

    #1

    // Check the result
    check_result('b000101010101, "I-type"); 

    // 3. ORI
    imm_type = 0;
    inst     = 'b111111111111_01010_110_10101_0010011;

    #1

    // Check the result
    check_result('b11111111111111111111_111111111111, "I-type"); 

    // 4. XORI
    imm_type = 0;
    inst     = 'b110000000001_01010_100_10101_0010011;

    #1

    // Check the result
    check_result('b11111111111111111111_110000000001, "I-type");

    // 5. SLTI
    imm_type = 0;
    inst     = 'b00000000011_01010_100_10101_0010011;

    #1

    // Check the result
    check_result('b00000000011, "I-type"); 

    // 6. SLTI
    imm_type = 0;
    inst     = 'b00001000011_01010_010_10101_0010011;

    #1

    // Check the result
    check_result('b00001000011, "I-type"); 

    // 7. SLTIU
    imm_type = 0;
    inst     = 'b111111000011_01010_011_10101_0010011;

    #1

    // Check the result
    check_result('b11111111111111111111_111111000011, "I-type");

    // 8. SRAI
    imm_type = 0;
    inst     = 'b0100000_01001_01010_101_10101_0010011;

    #1

    // Check the result
    check_result('b000000000000000000000_100000_01001, "I-type");  

    // 9. SRLI
    imm_type = 0;
    inst     = 'b0000000_10101_01010_101_10101_0010011;

    #1

    // Check the result
    check_result('b0000000_10101, "I-type");  

    // 10. SLLI
    imm_type = 0;
    inst     = 'b0000000_00101_01010_001_10101_0010011;

    #1

    // Check the result
    check_result('b0000000_00101, "I-type"); 

    // 11. LW
    imm_type = 0;
    inst     = 'b111111001001_10101_010_10101_0000011;

    #1

    // Check the result
    check_result('b11111111111111111111_111111001001, "I-type"); 

    // TODO: 12. JALR
  
    $finish();

  end

  task check_result(logic [31:0] expected, string immType);
    if (imm == expected) begin
      $display("%s immediate result is correct. Expected: %h, Actual: %h", immType, expected, imm); 
      pass();
    end else begin
      $display("%s immediate result is incorrect. Expected: %h, Actual: %h", immType, expected, imm); 
      fail(); 
      $finish();
    end
  endtask

endmodule

lab2_proc/waves/ProcDpathImmGen.utb_ProcDpathImmGen.v.waves.vcd
$version Generated by VerilatedVcd $end
$timescale 1ps $end

 $scope module top $end
  $var wire  1 # clk $end
  $var wire  1 $ linetrace $end
  $scope module top $end
   $var wire  1 # clk $end
   $var wire 32 ' imm [31:0] $end
   $var wire  3 % imm_type [2:0] $end
   $var wire 32 & inst [31:0] $end
   $var wire  1 $ linetrace $end
   $scope module DUT $end
    $var wire 32 ' imm [31:0] $end
    $var wire  3 % imm_type [2:0] $end
    $var wire 32 & inst [31:0] $end
   $upscope $end
  $upscope $end
 $upscope $end
$enddefinitions $end


#1
1#
0$
b000 %
b00000000000000000000000000000000 &
b00000000000000000000000000000000 '
#2
0#
b10010101010101010000101010010011 &
b11111111111111111111100101010101 '
#3
1#
b00010101010101010111101010010011 &
b00000000000000000000000101010101 '
#4
0#
b11111111111101010110101010010011 &
b11111111111111111111111111111111 '
#5
1#
b11000000000101010100101010010011 &
b11111111111111111111110000000001 '
#6
0#
b00000000001101010100101010010011 &
b00000000000000000000000000000011 '
#7
1#
b00000100001101010010101010010011 &
b00000000000000000000000001000011 '
#8
0#
b11111100001101010011101010010011 &
b11111111111111111111111111000011 '
#9
1#
b01000000100101010101101010010011 &
b00000000000000000000010000001001 '
#10
0#
b00000001010101010101101010010011 &
b00000000000000000000000000010101 '
#11
1#
b00000000010101010001101010010011 &
b00000000000000000000000000000101 '
#12
0#
b11111100100110101010101010000011 &
b11111111111111111111111111001001 '
